MANIFEST.in
README.md
VERSION
setup.py
tbtc/__init__.py
tbtc/bitcoin_helpers.py
tbtc/constants.py
tbtc/deposit.py
tbtc/electrum.py
tbtc/session.py
tbtc/settings.py
tbtc/tbtc_system.py
tbtc/utils.py
tbtc.egg-info/PKG-INFO
tbtc.egg-info/SOURCES.txt
tbtc.egg-info/dependency_links.txt
tbtc.egg-info/requires.txt
tbtc.egg-info/top_level.txt