Metadata-Version: 2.1
Name: tbtc
Version: 0.0.5
Summary: A python library to interact with the tbtc protocol.
Home-page: https://github.com/ankitchiplunkar/tbtc.py
Author: Ankit Chiplunkar
Author-email: ankitchiplunkar@gmail.com
License: UNKNOWN
Keywords: ethereum,bitcoin
Platform: UNKNOWN
Classifier: Development Status :: 3 - Alpha
Classifier: Intended Audience :: Developers
Classifier: Natural Language :: English
Classifier: Programming Language :: Python :: 3
Classifier: Programming Language :: Python :: 3.6
Requires-Python: >=3.6, <4
